gi-stubs/repository/Gst.pyi
gst-stubs/Gst.pyi
gst-stubs/__init__.pyi
gst-stubs/repository/Gst.pyi
gst-stubs/repository/__init__.pyi
gst_python_stubs-0.0.2.dist-info/DESCRIPTION.rst
gst_python_stubs-0.0.2.dist-info/METADATA
gst_python_stubs-0.0.2.dist-info/RECORD
gst_python_stubs-0.0.2.dist-info/WHEEL
gst_python_stubs-0.0.2.dist-info/metadata.json
gst_python_stubs-0.0.2.dist-info/top_level.txt
